BrainFuckPlusInterpreter/BrainFuckPlusInterpreter.py
BrainFuckPlusInterpreter/setup.py
sqlite_help_functions/__init__.py
sqlite_help_functions/main.py
sqlite_help_functions/setup.py
this_is_my_package_called_password/my_password.py
this_is_my_package_called_password/setup.py
this_is_my_package_called_password-2.0.0.dist-info/METADATA
this_is_my_package_called_password-2.0.0.dist-info/WHEEL
this_is_my_package_called_password-2.0.0.dist-info/top_level.txt
this_is_my_package_called_password-2.0.0.dist-info/RECORD
