Metadata-Version: 2.1
Name: this-is-my-package-called-password
Version: 2.0.0
Summary: Password validator and generator
Home-page: https://github.com/TvoozMagnificent/password
Author: TvoozMagnificent
Author-email: luchang1106@icloud.com
License: MIT
Platform: UNKNOWN
Classifier: License :: OSI Approved :: MIT License
Classifier: Programming Language :: Python :: 3
Classifier: Programming Language :: Python :: 3.7
